{
  "$schema": "http://json-schema.org/draft-07/schema#",
  "title": "Super Comprehensive Schema",
  "type": "object",
  "properties": {
    "SampleID": {
      "type": [
        "string",
        "null"
      ]
    },
    "Height_cm": {
      "type": [
        "number",
        "null"
      ],
      "minimum": 30,
      "maximum": 250
    },
    "Weight_kg": {
      "type": [
        "number",
        "null"
      ],
      "minimum": 1,
      "maximum": 400
    },
    "Cholesterol_mgdl": {
      "type": [
        "number",
        "null"
      ],
      "minimum": 50,
      "maximum": 600
    },
    "BP_systolic": {
      "type": [
        "number",
        "null"
      ],
      "minimum": 50,
      "maximum": 250
    },
    "BP_diastolic": {
      "type": [
        "number",
        "null"
      ],
      "minimum": 30,
      "maximum": 200
    },
    "Glucose_mgdl": {
      "type": [
        "number",
        "null"
      ],
      "minimum": 20,
      "maximum": 800
    },
    "Creatinine_mgdl": {
      "type": [
        "number",
        "null"
      ],
      "minimum": 0.1,
      "maximum": 20
    },
    "PrimaryPhenotype": {
      "type": [
        "string",
        "null"
      ]
    },
    "DiseaseCode": {
      "type": [
        "string",
        "null"
      ]
    },
    "VisitDate": {
      "type": [
        "string",
        "null"
      ]
    },
    "class": {
      "type": [
        "string",
        "null"
      ]
    }
  },
  "required": [
    "SampleID"
  ]
}