{
  "file": "data.csv",
  "quality_scores": {
    "Schema Validation Score": 100.0,
    "Missing Data Score": 92.5,
    "Mapping Success Score": 0.0,
    "Overall Quality Score": 64.16666666666667
  },
  "imputation": {
    "global": {
      "strategy": "knn",
      "params": {
        "n_neighbors": 3
      }
    },
    "tuning": {
      "enabled": true,
      "best": {
        "n_neighbors": 5
      },
      "score": 52.23679191193055,
      "metric": "MAE",
      "random_state": 42,
      "mask_fraction": 0.1
    }
  },
  "class_distribution": null,
  "quality_metrics": {
    "imputation_bias": {
      "rows": [
        {
          "column": "feat1",
          "n_obs": 640,
          "n_imp": 160,
          "mean_diff": -0.0033510230449707162,
          "smd": -0.016541488912007397,
          "var_ratio": 0.8614638262293006,
          "ks_stat": 0.1859375,
          "ks_p": 0.0002551854584892803,
          "warn": true,
          "wdist": 0.3725745908776352,
          "low_n": false
        },
        {
          "column": "feat2",
          "n_obs": 640,
          "n_imp": 160,
          "mean_diff": 0.010507104612739404,
          "smd": 0.02606312660789924,
          "var_ratio": 0.8862642473801363,
          "ks_stat": 0.1453125,
          "ks_p": 0.008378344334231909,
          "warn": true,
          "wdist": 0.6359724909732204,
          "low_n": false
        },
        {
          "column": "feat3",
          "n_obs": 640,
          "n_imp": 160,
          "mean_diff": -0.012593176548261198,
          "smd": -0.02080120287170181,
          "var_ratio": 0.8418822123355778,
          "ks_stat": 0.3109375,
          "ks_p": 2.065822063014829e-11,
          "warn": true,
          "wdist": 1.5599857645346682,
          "low_n": false
        }
      ]
    },
    "imputation_stability": {
      "rows": [
        {
          "column": "feat1",
          "repeats": 5,
          "metric": "RMSE",
          "mean_error": 0.5944820239697824,
          "sd_error": 0.07001126954139832,
          "cv_error": 0.11776852237496249
        },
        {
          "column": "outcome",
          "repeats": 5,
          "metric": "RMSE",
          "mean_error": 0.29362253438910557,
          "sd_error": 0.029517227528836457,
          "cv_error": 0.10052780039600274
        },
        {
          "column": "feat2",
          "repeats": 5,
          "metric": "RMSE",
          "mean_error": 1.1522745189034853,
          "sd_error": 0.10711526245850225,
          "cv_error": 0.09295984654805531
        },
        {
          "column": "SampleID",
          "repeats": 5,
          "metric": "RMSE",
          "mean_error": 274.64868522017207,
          "sd_error": 23.82699004474079,
          "cv_error": 0.08675442966581066
        },
        {
          "column": "feat3",
          "repeats": 5,
          "metric": "RMSE",
          "mean_error": 3.335124610734647,
          "sd_error": 0.2524765110035187,
          "cv_error": 0.07570227217024561
        }
      ]
    },
    "imputation_uncertainty": {
      "rows": []
    }
  }
}